[
  {
    "name": ["Bread", "Earl Grey Tea"],
    "firstName": "John",
    "lastName": "Doe",
    "venmo": "johnd1",
    "image": "https://i.insider.com/5df126b679d7570ad2044f3e?width=1100&format=jpeg&auto=webp",
    "store": "Starbucks",
    "owner": "admin@foo.com",
    "quantity": [1, 1],
    "personWhoOrdered": "john@foo.com",
    "location": "1000 Pope Rd, Honolulu, HI 96822",
    "size": ["Small", "Large"],
    "cost": 15.43,
    "lat": 21.2984,
    "long": 157.8205
  },
  {
    "name": ["Chicken"],
    "firstName": "Admin",
    "lastName": "Doe",
    "venmo": "admindoe",
    "image": "https://react.semantic-ui.com/images/avatar/large/patrick.png",
    "store": "Bale",
    "owner": "john@foo.com",
    "quantity": [2],
    "personWhoOrdered": "admin@foo.com",
    "location": "Sinclair Building (former library, 2425 Campus Rd, Honolulu, HI 96822",
    "size": ["Large"],
    "cost": 15.50,
    "lat": 21.2974,
    "long": 157.8165
  }
]